betternot/__init__.py
betternot/credentials.py
betternot/findingchart.py
betternot/fritz.py
betternot/io.py
betternot/observability.py
betternot/utils.py
betternot/wiserep.py
betternot-0.1.3.dist-info/LICENSE
betternot-0.1.3.dist-info/METADATA
betternot-0.1.3.dist-info/WHEEL
betternot-0.1.3.dist-info/entry_points.txt
betternot-0.1.3.dist-info/RECORD
