Metadata-Version: 2.1
Name: betternot
Version: 0.1.3
Summary: Toolset for interacting with the Nordic Optical Telescope (NOT)
License: BSD-3-Clause
Author: simeonreusch
Author-email: simeon.reusch@desy.de
Requires-Python: >=3.9,<3.12
Classifier: License :: OSI Approved :: BSD License
Classifier: Programming Language :: Python :: 3
Classifier: Programming Language :: Python :: 3.9
Classifier: Programming Language :: Python :: 3.10
Classifier: Programming Language :: Python :: 3.11
Requires-Dist: astroplan (>=0.9)
Requires-Dist: astropy (>=5.0,<6.0)
Requires-Dist: backoff (>=1.10.0,<2.0.0)
Requires-Dist: importlib-metadata (>=6.7.0)
Requires-Dist: keyring (>=23.7.0,<24.0.0)
Requires-Dist: matplotlib (>=3.5.0)
Requires-Dist: numpy (>=1.21.0,<2.0.0)
Requires-Dist: pandas (>=1.2.5)
Requires-Dist: pypeit (>=1.13.0,<2.0.0)
Requires-Dist: requests (>=2.23.0)
Requires-Dist: ztfquery (>=1.20.0)
